mcnn/__init__.py
mcnn/nn/__init__.py
mcnn/nn/parameter.py
mcnn/nn/manifolds/__init__.py
mcnn/nn/manifolds/complex_circle.py
mcnn/nn/manifolds/complex_euclidean.py
mcnn/nn/manifolds/complex_sphere.py
mcnn/nn/manifolds/complex_stiefel.py
mcnn/nn/manifolds/manifold.py
mcnn/nn/manifolds/manifold_factory.py
mcnn/nn/modules/__init__.py
mcnn/nn/modules/conv.py
mcnn/nn/modules/linear.py
mcnn/nn/modules/rnn.py
mcnn/nn/modules/utils.py
mcnn/nn/utils/__init__.py
mcnn/nn/utils/manifold_multi.py
mcnn/optim/__init__.py
mcnn/optim/conjugate_gradient.py
mcnn/optim/manifold_RMSprop.py
mcnn/optim/manifold_adagrad.py
mcnn/optim/manifold_adam.py
mcnn/optim/manifold_sgd.py
mcnn/optim/quantified_manifold_RMSprop.py
mcnn/optim/quantified_manifold_adagrad.py
mcnnlib-1.0.2.dist-info/LICENSE
mcnnlib-1.0.2.dist-info/METADATA
mcnnlib-1.0.2.dist-info/WHEEL
mcnnlib-1.0.2.dist-info/top_level.txt
mcnnlib-1.0.2.dist-info/RECORD
