Metadata-Version: 2.1
Name: mcnnlib
Version: 1.0.2
Summary: Constrained Optimization and Manifold Optimization in Pytorch
Home-page: https://github.com/HuangQiang97/mcnn
Author: huang chiang
Author-email: huangqiang97@126.com
License: MIT
Keywords: Constrained Optimization,Optimization on Manifolds,Pytorch
Classifier: Programming Language :: Python :: 3
Classifier: License :: OSI Approved :: MIT License
Classifier: Operating System :: OS Independent
Requires-Python: >=3.5
License-File: LICENSE
Requires-Dist: torch (>=1.9)
